discord_kartrider/kartrider.py
discord_kartrider-1.0.6.1.dist-info/METADATA
discord_kartrider-1.0.6.1.dist-info/WHEEL
discord_kartrider-1.0.6.1.dist-info/top_level.txt
discord_kartrider-1.0.6.1.dist-info/RECORD
