Metadata-Version: 2.1
Name: discord-kartrider
Version: 1.0.6.1
Summary: 넥슨 API, BAZZI를 이용한 크롤링
Home-page: https://github.com/chunjoonseo541/discord-kartrider
Author: joonseo7397
Author-email: joonseo5411@gmail.com
License: MIT
Platform: UNKNOWN
Classifier: Programming Language :: Python :: 3.5
Classifier: Programming Language :: Python :: 3.6
Classifier: Programming Language :: Python :: 3.7
Classifier: Programming Language :: Python :: 3.8
Classifier: Programming Language :: Python :: 3.9
Classifier: Programming Language :: Python :: 3.10
Requires-Python: >=3.5
Requires-Dist: beautifulsoup4
Requires-Dist: requests
